{
  "type": "minecraft:crafting_shaped",
  "category": "misc",
  "key": {
    "A": {
      "item": "create:andesite_alloy"
    },
    "C": {
      "tag": "forge:tools/screwdrivers"
    },
    "I": [
      {
        "item": "gtceu:rubber_ring"
      },
      {
        "item": "gtceu:silicone_rubber_ring"
      }
    ],
    "N": {
      "tag": "forge:nuggets/iron"
    },
    "O": {
      "tag": "greate:cogwheels/andesite"
    },
    "P": {
      "item": "create:fluid_pipe"
    },
    "W": {
      "tag": "forge:tools/wrenches"
    }
  },
  "pattern": [
    "NAI",
    "COW",
    "IP "
  ],
  "result": {
    "item": "greate:andesite_mechanical_pump"
  },
  "show_notification": true
}